stm32cubeprog/__init__.py
stm32cubeprog/cli.py
stm32cubeprog-0.1.2.dist-info/licenses/LICENCE
stm32cubeprog-0.1.2.dist-info/METADATA
stm32cubeprog-0.1.2.dist-info/WHEEL
stm32cubeprog-0.1.2.dist-info/entry_points.txt
stm32cubeprog-0.1.2.dist-info/top_level.txt
stm32cubeprog-0.1.2.dist-info/RECORD
