Metadata-Version: 2.4
Name: stm32cubeprog
Version: 0.1.2
Summary: Python wrapper + CLI for STM32CubeProgrammer
Author: raj_cks
Project-URL: Homepage, https://github.com/rajcks007/stm32cubeprog
Project-URL: Repository, https://github.com/rajcks007/stm32cubeprog
Project-URL: Issues, https://github.com/rajcks007/stm32cubeprog/issues
Keywords: stm32,stm32cubeprogrammer,stlink,embedded,flashing,dfu
Classifier: Programming Language :: Python :: 3
Classifier: Programming Language :: Python :: 3 :: Only
Classifier: License :: OSI Approved :: MIT License
Classifier: Operating System :: OS Independent
Classifier: Environment :: Console
Classifier: Topic :: Software Development :: Build Tools
Classifier: Topic :: System :: Hardware :: Hardware Drivers
Requires-Python: >=3.8
License-File: LICENCE
Dynamic: license-file
